AUTHORS
CHANGELOG
INSTALL
LICENSE
MANIFEST.in
README.md
setup.py
accounts/__init__.py
accounts/admin.py
accounts/forms.py
accounts/models.py
accounts/settings.py
accounts/tests.py
accounts/urls.py
accounts/views.py
accounts/templates/.DS_Store
accounts/templates/registration/activation_confirm.html
accounts/templates/registration/activation_email.html
accounts/templates/registration/activation_email_title.txt
accounts/templates/registration/login.html
accounts/templates/registration/register_form.html
django_custom_accounts.egg-info/PKG-INFO
django_custom_accounts.egg-info/SOURCES.txt
django_custom_accounts.egg-info/dependency_links.txt
django_custom_accounts.egg-info/requires.txt
django_custom_accounts.egg-info/top_level.txt