Metadata-Version: 1.1
Name: django-custom-accounts
Version: 0.1
Summary: A custom accounts application for Django
Home-page: https://github.com/nekrox/django-custom-accounts
Author: Alvaro Lizama
Author-email: nekrox@gmail.com
License: MIT License
Download-URL: https://github.com/nekrox/django-custom-accounts/archive/master.tgz
Keywords: django custom user auth model email without username
Platform: UNKNOWN
Classifier: Development Status :: 5 - Production/Stable
Classifier: Environment :: Web Environment
Classifier: Framework :: Django
Classifier: Intended Audience :: Developers
Classifier: License :: OSI Approved :: MIT License
Classifier: Operating System :: OS Independent
Classifier: Programming Language :: Python
Classifier: Topic :: Software Development :: Libraries :: Python Modules
Classifier: Topic :: Utilities
